get_mysqldb/__init__.py
get_mysqldb-0.0.6.dist-info/METADATA
get_mysqldb-0.0.6.dist-info/WHEEL
get_mysqldb-0.0.6.dist-info/top_level.txt
get_mysqldb-0.0.6.dist-info/RECORD
