Metadata-Version: 2.4
Name: get_mysqldb
Version: 0.0.6
Summary: mysql数据存储
Author: MindLullaby
Author-email: 3203939025@qq.com
Requires-Dist: pymysql
Requires-Dist: loguru
Requires-Dist: dbutils==3.1.0
Dynamic: author
Dynamic: author-email
Dynamic: requires-dist
Dynamic: summary
